Metadata-Version: 2.1
Name: api-sap
Version: 1.0.1
Summary: API de acesso ao SAP.
Home-page: UNKNOWN
Author: Wilton Melo
Author-email: pmelo.wilton@gmail.com
License: MIT License
Keywords: api sap,SAP,conectar ao SAP
Platform: UNKNOWN
License-File: LICENCE
